LICENSE
MANIFEST.in
README.rst
setup.cfg
setup.py
django_choice_enumfields.egg-info/PKG-INFO
django_choice_enumfields.egg-info/SOURCES.txt
django_choice_enumfields.egg-info/dependency_links.txt
django_choice_enumfields.egg-info/not-zip-safe
django_choice_enumfields.egg-info/top_level.txt
enumfields/__init__.py
enumfields/admin.py
enumfields/enums.py
enumfields/fields.py
enumfields/forms.py
enumfields/drf/__init__.py
enumfields/drf/fields.py
enumfields/drf/serializers.py